py_expose_html/__init__.py
py_expose_html/expose.py
py_expose_html/version.py
PyExposeHtml-0.0.2.dist-info/LICENSE
PyExposeHtml-0.0.2.dist-info/METADATA
PyExposeHtml-0.0.2.dist-info/WHEEL
PyExposeHtml-0.0.2.dist-info/top_level.txt
PyExposeHtml-0.0.2.dist-info/RECORD
