Metadata-Version: 2.1
Name: PyExposeHtml
Version: 0.0.2
Summary: A package that helps you to scrap web pages. It shows you a lot of information about the page.
Author-email: Joao Paulo de Castro Lima <joao@paulo.com>
Project-URL: Homepage, https://github.com/joao2391/pyexpose
Project-URL: Issues, https://github.com/joao2391/pyexpose/issues
Classifier: Programming Language :: Python :: 3
Classifier: License :: OSI Approved :: MIT License
Classifier: Operating System :: OS Independent
Requires-Python: >=3.8
License-File: LICENSE
